moesif_aws_lambda/__init__.py
moesif_aws_lambda/client_ip.py
moesif_aws_lambda/global_variable.py
moesif_aws_lambda/middleware.py
moesif_aws_lambda/update_companies.py
moesif_aws_lambda/update_users.py
moesif_aws_lambda/tests/__init__.py
moesif_aws_lambda/tests/tests.py
moesif_aws_lambda-1.2.3.dist-info/licenses/LICENSE
moesif_aws_lambda-1.2.3.dist-info/METADATA
moesif_aws_lambda-1.2.3.dist-info/WHEEL
moesif_aws_lambda-1.2.3.dist-info/top_level.txt
moesif_aws_lambda-1.2.3.dist-info/RECORD
