Metadata-Version: 2.4
Name: moesif_aws_lambda
Version: 1.2.3
Summary: Moesif Middleware to automatically log API calls from AWS Lambda functions
Home-page: https://www.moesif.com/docs/server-integration/aws-lambda-python/
Author: Moesif, Inc
Author-email: keyur@moesif.com
License: Apache Software License
Keywords: moesif aws serverless api gateway lambda debug logging trace analytics
Classifier: Development Status :: 4 - Beta
Classifier: Intended Audience :: Developers
Classifier: Topic :: Internet :: Log Analysis
Classifier: Topic :: Software Development :: Debuggers
Classifier: Topic :: Software Development :: Libraries
Classifier: Topic :: Internet :: WWW/HTTP
Classifier: License :: OSI Approved :: Apache Software License
Classifier: Programming Language :: Python :: 2
Classifier: Programming Language :: Python :: 2.6
Classifier: Programming Language :: Python :: 2.7
Classifier: Programming Language :: Python :: 3
Classifier: Programming Language :: Python :: 3.3
Classifier: Programming Language :: Python :: 3.4
Classifier: Programming Language :: Python :: 3.5
Classifier: Programming Language :: Python :: 3.6
Classifier: Programming Language :: Python :: 3.7
License-File: LICENSE
Requires-Dist: moesifapi>=1.5.5
Requires-Dist: lambda_decorators
Requires-Dist: moesifpythonrequest>=0.3.5
Provides-Extra: dev
Provides-Extra: test
Requires-Dist: nose; extra == "test"
Dynamic: author
Dynamic: author-email
Dynamic: classifier
Dynamic: description
Dynamic: description-content-type
Dynamic: home-page
Dynamic: keywords
Dynamic: license
Dynamic: license-file
Dynamic: provides-extra
Dynamic: requires-dist
Dynamic: summary
